<annotation>
	<folder>dataset</folder>
	<filename>image_1083.jpg</filename>
	<path>C:\Users\Thoi\Desktop\label\data\dataset\image_1083.jpg</path>
	<source>
		<database>Unknown</database>
	</source>
	<size>
		<width>816</width>
		<height>506</height>
		<depth>3</depth>
	</size>
	<segmented>0</segmented>
	<object>
		<name>tren_trai</name>
		<pose>Unspecified</pose>
		<truncated>0</truncated>
		<difficult>0</difficult>
		<bndbox>
			<xmin>93</xmin>
			<ymin>49</ymin>
			<xmax>125</xmax>
			<ymax>77</ymax>
		</bndbox>
	</object>
	<object>
		<name>tren_phai</name>
		<pose>Unspecified</pose>
		<truncated>0</truncated>
		<difficult>0</difficult>
		<bndbox>
			<xmin>596</xmin>
			<ymin>55</ymin>
			<xmax>627</xmax>
			<ymax>79</ymax>
		</bndbox>
	</object>
	<object>
		<name>duoi_phai</name>
		<pose>Unspecified</pose>
		<truncated>0</truncated>
		<difficult>0</difficult>
		<bndbox>
			<xmin>610</xmin>
			<ymin>368</ymin>
			<xmax>644</xmax>
			<ymax>397</ymax>
		</bndbox>
	</object>
	<object>
		<name>duoi_trai</name>
		<pose>Unspecified</pose>
		<truncated>0</truncated>
		<difficult>0</difficult>
		<bndbox>
			<xmin>83</xmin>
			<ymin>379</ymin>
			<xmax>117</xmax>
			<ymax>406</ymax>
		</bndbox>
	</object>
	<object>
		<name>quochieu</name>
		<pose>Unspecified</pose>
		<truncated>0</truncated>
		<difficult>0</difficult>
		<bndbox>
			<xmin>146</xmin>
			<ymin>88</ymin>
			<xmax>233</xmax>
			<ymax>172</ymax>
		</bndbox>
	</object>
	<object>
		<name>the</name>
		<pose>Unspecified</pose>
		<truncated>0</truncated>
		<difficult>0</difficult>
		<bndbox>
			<xmin>86</xmin>
			<ymin>53</ymin>
			<xmax>639</xmax>
			<ymax>408</ymax>
		</bndbox>
	</object>
</annotation>
