<annotation>
	<folder>dataset</folder>
	<filename>image_111.jpg</filename>
	<path>C:\Users\Thoi\Desktop\label\data\dataset\image_111.jpg</path>
	<source>
		<database>Unknown</database>
	</source>
	<size>
		<width>1280</width>
		<height>960</height>
		<depth>3</depth>
	</size>
	<segmented>0</segmented>
	<object>
		<name>tren_trai</name>
		<pose>Unspecified</pose>
		<truncated>0</truncated>
		<difficult>0</difficult>
		<bndbox>
			<xmin>81</xmin>
			<ymin>61</ymin>
			<xmax>137</xmax>
			<ymax>114</ymax>
		</bndbox>
	</object>
	<object>
		<name>tren_phai</name>
		<pose>Unspecified</pose>
		<truncated>0</truncated>
		<difficult>0</difficult>
		<bndbox>
			<xmin>1197</xmin>
			<ymin>85</ymin>
			<xmax>1256</xmax>
			<ymax>133</ymax>
		</bndbox>
	</object>
	<object>
		<name>duoi_phai</name>
		<pose>Unspecified</pose>
		<truncated>0</truncated>
		<difficult>0</difficult>
		<bndbox>
			<xmin>1216</xmin>
			<ymin>816</ymin>
			<xmax>1277</xmax>
			<ymax>877</ymax>
		</bndbox>
	</object>
	<object>
		<name>duoi_trai</name>
		<pose>Unspecified</pose>
		<truncated>1</truncated>
		<difficult>0</difficult>
		<bndbox>
			<xmin>1</xmin>
			<ymin>767</ymin>
			<xmax>47</xmax>
			<ymax>829</ymax>
		</bndbox>
	</object>
	<object>
		<name>quochieu</name>
		<pose>Unspecified</pose>
		<truncated>0</truncated>
		<difficult>0</difficult>
		<bndbox>
			<xmin>183</xmin>
			<ymin>143</ymin>
			<xmax>364</xmax>
			<ymax>324</ymax>
		</bndbox>
	</object>
	<object>
		<name>the</name>
		<pose>Unspecified</pose>
		<truncated>1</truncated>
		<difficult>0</difficult>
		<bndbox>
			<xmin>1</xmin>
			<ymin>68</ymin>
			<xmax>1270</xmax>
			<ymax>869</ymax>
		</bndbox>
	</object>
</annotation>
